pySpaceTraders/__init__.py
pySpaceTraders/api.py
pySpaceTraders/constants.py
pySpaceTraders/models/enums.py
pySpaceTraders/models/models.py
pySpaceTraders/utils/pySpaceLimiter.py
pySpaceTraders/utils/pySpaceLogger.py
pySpaceTraders/utils/pySpaceParsers.py
pySpaceTraders/utils/pySpaceRequest.py
pyspacetraders-0.5.0.dist-info/LICENSE
pyspacetraders-0.5.0.dist-info/METADATA
pyspacetraders-0.5.0.dist-info/WHEEL
pyspacetraders-0.5.0.dist-info/RECORD
