Metadata-Version: 2.1
Name: pySpaceTraders
Version: 0.5.0
Summary: An API wrapper for the SpaceTraders API game
Home-page: https://github.com/chatterchats/pySpaceTrader
License: MIT
Author: Chatterchats
Author-email: chats@irby.us
Maintainer: Kejax
Maintainer-email: kejax@kejax.net
Requires-Python: >=3.12.4,<3.13.0
Classifier: Development Status :: 4 - Beta
Classifier: Intended Audience :: Developers
Classifier: License :: OSI Approved :: MIT License
Classifier: Operating System :: OS Independent
Classifier: Programming Language :: Python :: 3
Classifier: Programming Language :: Python :: 3.12
Requires-Dist: dacite (>=1.8.1,<1.9.0)
Requires-Dist: httpx (>=0.27.0,<0.28.0)
Project-URL: Repository, https://github.com/chatterchats/pySpaceTrader
